trytond/modules/health/COPYING
trytond/modules/health/README.rst
trytond/modules/health/__init__.py
trytond/modules/health/core.py
trytond/modules/health/country.py
trytond/modules/health/data/dose_units.xml
trytond/modules/health/data/drug_administration_routes.xml
trytond/modules/health/data/ethnic_groups.xml
trytond/modules/health/data/gnuhealth_commands.xml
trytond/modules/health/data/health_product.xml
trytond/modules/health/data/health_sequences.xml
trytond/modules/health/data/health_specialties.xml
trytond/modules/health/data/help/help.xml
trytond/modules/health/data/medicament_form.xml
trytond/modules/health/data/medication_frequencies.xml
trytond/modules/health/data/messages/messages.xml
trytond/modules/health/data/occupations.xml
trytond/modules/health/data/online_document.xml
trytond/modules/health/data/pathology_groups.xml
trytond/modules/health/exceptions.py
trytond/modules/health/health.py
trytond/modules/health/health_report.xml
trytond/modules/health/health_view.xml
trytond/modules/health/icons/appointment.svg
trytond/modules/health/icons/bol.svg
trytond/modules/health/icons/cancel.svg
trytond/modules/health/icons/demography.svg
trytond/modules/health/icons/doctor.svg
trytond/modules/health/icons/face-sick.svg
trytond/modules/health/icons/federation.svg
trytond/modules/health/icons/gnuhealth_icon.svg
trytond/modules/health/icons/gnuhealth_nurse.svg
trytond/modules/health/icons/hand-scalpel.svg
trytond/modules/health/icons/health-center.svg
trytond/modules/health/icons/help.svg
trytond/modules/health/icons/immunizations.svg
trytond/modules/health/icons/medicament.svg
trytond/modules/health/icons/ok.svg
trytond/modules/health/icons/online_document.svg
trytond/modules/health/icons/patient.svg
trytond/modules/health/icons/prescription.svg
trytond/modules/health/icons/report.svg
trytond/modules/health/icons/stop.svg
trytond/modules/health/icons/tryton-currency.svg
trytond/modules/health/icons/tryton-list.svg
trytond/modules/health/icons/tryton-open.svg
gnuhealth-5.0.4.dist-info/METADATA
gnuhealth-5.0.4.dist-info/WHEEL
gnuhealth-5.0.4.dist-info/licenses/COPYING
gnuhealth-5.0.4.dist-info/RECORD
