Metadata-Version: 2.4
Name: gnuhealth
Version: 5.0.4
Summary: GNU Health Hospital and Health Information System. Core package
License: GPL-3.0-or-later
License-File: COPYING
Keywords: health,hospital,HIS,eHealth,gnuhealth
Author: GNU Solidario
Author-email: info@gnusolidario.org
Maintainer: Luis Falcon
Maintainer-email: falcon@gnuhealth.org
Requires-Python: >=3.10,<3.15
Classifier: Development Status :: 5 - Production/Stable
Classifier: Environment :: Plugins
Classifier: Framework :: Tryton
Classifier: Intended Audience :: Developers
Classifier: Intended Audience :: Healthcare Industry
Classifier: License :: OSI Approved :: GNU General Public License v3 or later (GPLv3+)
Classifier: Natural Language :: English
Classifier: Operating System :: OS Independent
Classifier: Programming Language :: Python :: 3
Classifier: Programming Language :: Python :: 3.10
Classifier: Programming Language :: Python :: 3.11
Classifier: Programming Language :: Python :: 3.12
Classifier: Programming Language :: Python :: 3.13
Classifier: Programming Language :: Python :: 3.14
Classifier: Topic :: Scientific/Engineering :: Bio-Informatics
Classifier: Topic :: Scientific/Engineering :: Medical Science Apps.
Requires-Dist: gnuhealth-control (>=5.0.0,<5.1)
Requires-Dist: matplotlib
Requires-Dist: pillow
Requires-Dist: pytz
Requires-Dist: trytond (>=7.0,<7.1)
Requires-Dist: trytond-company (>=7.0,<7.1)
Requires-Dist: trytond-currency (>=7.0,<7.1)
Requires-Dist: trytond-party (>=7.0,<7.1)
Requires-Dist: trytond-product (>=7.0,<7.1)
Project-URL: Bug Tracker, https://codeberg.org/gnuhealth/his/issues
Project-URL: Documentation, https://docs.gnuhealth.org
Project-URL: Homepage, https://www.gnuhealth.org
Project-URL: Repository, https://codeberg.org/gnuhealth/his
